LICENSE
MANIFEST.in
README.rst
setup.py
django_yubico/__init__.py
django_yubico/admin.py
django_yubico/backends.py
django_yubico/forms.py
django_yubico/models.py
django_yubico/urls.py
django_yubico/views.py
django_yubico.egg-info/PKG-INFO
django_yubico.egg-info/SOURCES.txt
django_yubico.egg-info/dependency_links.txt
django_yubico.egg-info/requires.txt
django_yubico.egg-info/top_level.txt
django_yubico/site_media/images/yubiright_16x16.gif
django_yubico/templates/django_yubico/login.html
django_yubico/templates/django_yubico/password.html