Metadata-Version: 1.1
Name: django-yubico
Version: 0.3.0
Summary: Yubico Yubikey authentication backend for Django
Home-page: http://github.com/Kami/django-yubico-authentication-backend/
Author: Tomaz Muraus
Author-email: tomaz+pypi@tomaz.me
License: BSD
Platform: UNKNOWN
Classifier: Development Status :: 3 - Alpha
Classifier: Environment :: Web Environment
Classifier: Framework :: Django
Classifier: Intended Audience :: Developers
Classifier: License :: OSI Approved :: BSD License
Classifier: Operating System :: OS Independent
Classifier: Programming Language :: Python
Classifier: Topic :: Internet :: WWW/HTTP
Classifier: Topic :: Security
Classifier: Topic :: Software Development :: Libraries
Provides: django_yubico
